src/axi_module_ready.v
//////////////////////////////////////////////////////////////////////////////////
// Engineer:
// 
// Create Date: 2022/11/13 16:16:32
// Design Name: 
// Module Name: 
// Description: 
// 
// Dependencies: 
// 
// Revision:
// Revision 0.01 - File Created
// Additional Comments:
// ready需要打拍的代码

`timescale  1ns/1ps
// ready_i打拍进来，但仍然可用ready_i
// 反压无法立即传到到上个模块，必须逐级打拍反压了
// 输出是一级级出的，去已经发送出去的就找不回来
module axi_module_ready #(
    parameter DWIDTH = 8
)
(
    input                   aclk_i,
    input                   areset_i,

    // down-stream
    input                   ready_i,
    output                  valid_o,
    output  [DWIDTH-1:0]    data_o,

    // up-stream
    output                  ready_o,
    input                   valid_i,
    input  [DWIDTH-1:0]     data_i   
);

reg [DWIDTH-1:0]    expansion_data_reg;
reg                 expansion_valid_reg;
reg                 ready_i_reg;
reg [DWIDTH-1:0]    data_reg;
reg                 valid_reg;

// 不再是用之前的~valid_o | ready_i
assign  ready_o = ~expansion_valid_reg;
assign  data_o  = expansion_valid_reg ? expansion_data_reg : data_reg;
// 只要expansion里有valid数据或上游有valid数据，输出就是valid
assign  valid_o = expansion_valid_reg | valid_reg;

always @(posedge aclk_i) begin
    if(areset_i) begin
        data_reg            <= 'd0;
        valid_reg           <= 'd0;
        expansion_data_reg  <= 'd0;
        expansion_valid_reg <= 'd0;
    end
    else begin
        if(ready_o) begin
            data_reg    <= data_i + 1'b1;
            valid_reg     <= valid_i;
            if(~ready_i) begin
                expansion_data_reg  <= data_reg;
                expansion_valid_reg <= valid_reg;
            end
        end
        // 当下游准备好接收时，需要清空expansion valid
        if(ready_i)
            expansion_valid_reg <= 'd0;
    end
end






endmodule

tb/tb.v
`timescale 1ns/1ps

module tb();

localparam DWIDTH = 8;

reg                 aclk        = 'd0;
reg                 slow_clk    = 'd0;
reg                 areset      = 'd0;
reg                 up_valid    = 'd0;
wire                up_ready;
wire                down_ready, down_valid;
wire                last_valid;
reg                 last_ready  = 'd0;
reg [DWIDTH-1:0]    up_data     = 'd0; 
wire[DWIDTH-1:0]    down_data, last_data;

always #5   aclk = ~aclk;
always #100 slow_clk = ~slow_clk;

// 产生随机数据
always @(posedge aclk) begin
    if(up_ready == 1'b1 && up_valid)
        up_data <= $random();
    else
        up_data <= up_data;
end

always @(posedge slow_clk) begin
    up_valid    <= $random();
end

always @(posedge slow_clk) begin
    last_ready  <= $random();
end

initial begin
    areset = 'd1;
    #100
    areset = 'd0;
    #100000
    // // 连续传输情况，无气泡
    // up_valid    = 'd1;
    // last_ready  = 'd1;
    // if(up_ready == 1'b0)
    //     $display("Error! Must transfer continuously!");
    // #200

    // // 无有效数据传输情况
    // up_valid = 'd0;
    // #100
    // up_valid = 'd1;
    // #100

    // // 反压情况
    // last_ready = 'd0;
    // #100
    // up_valid   = 'd0;
    // last_ready = 'd1;
    // #100


    $finish;
end


axi_module_ready #(.DWIDTH(DWIDTH)) master
(
    .aclk_i     (aclk),
    .areset_i   (areset),
    .ready_i    (down_ready),
    .valid_o    (down_valid),
    .data_o     (down_data),
    .ready_o    (up_ready),
    .valid_i    (up_valid),
    .data_i     (up_data)  
);

axi_module_ready #(.DWIDTH(DWIDTH)) slave
(
    .aclk_i     (aclk),
    .areset_i   (areset),
    .ready_i    (last_ready),
    .valid_o    (last_valid),
    .data_o     (last_data),
    .ready_o    (down_ready),
    .valid_i    (down_valid),
    .data_i     (down_data)  
);



endmodule

vcd/axi_module_ready.vcd
$date
   Thu Nov 17 17:29:47 2022
$end
$version
  2020.2
$end
$timescale
  1ps
$end
$scope module tb $end
$var reg 1 : aclk $end
$var reg 1 ; slow_clk $end
$var reg 1 < areset $end
$var reg 1 = up_valid $end
$var wire 1 & up_ready $end
$var wire 1 # down_ready $end
$var wire 1 $ down_valid $end
$var wire 1 2 last_valid $end
$var reg 1 > last_ready $end
$var reg 8 ? up_data [7:0] $end
$var wire 8 % down_data [7:0] $end
$var wire 8 3 last_data [7:0] $end
$var parameter 32 @ DWIDTH [31:0] $end
$scope module master $end
$var wire 1 ! aclk_i $end
$var wire 1 " areset_i $end
$var wire 1 # ready_i $end
$var wire 1 $ valid_o $end
$var wire 8 % data_o [7:0] $end
$var wire 1 & ready_o $end
$var wire 1 ' valid_i $end
$var wire 8 ( data_i [7:0] $end
$var reg 8 ) expansion_data_reg [7:0] $end
$var reg 1 * expansion_valid_reg $end
$var reg 1 + ready_i_reg $end
$var reg 8 , data_reg [7:0] $end
$var reg 1 - valid_reg $end
$var parameter 32 . DWIDTH [31:0] $end
$upscope $end
$scope module slave $end
$var wire 1 / aclk_i $end
$var wire 1 0 areset_i $end
$var wire 1 1 ready_i $end
$var wire 1 2 valid_o $end
$var wire 8 3 data_o [7:0] $end
$var wire 1 # ready_o $end
$var wire 1 $ valid_i $end
$var wire 8 % data_i [7:0] $end
$var reg 8 4 expansion_data_reg [7:0] $end
$var reg 1 5 expansion_valid_reg $end
$var reg 1 6 ready_i_reg $end
$var reg 8 7 data_reg [7:0] $end
$var reg 1 8 valid_reg $end
$var parameter 32 9 DWIDTH [31:0] $end
$upscope $end
$upscope $end
$enddefinitions $end
#0
$dumpvars
0!
1"
x#
x$
bx %
x&
0'
b0 (
bx )
x*
x+
bx ,
x-
b1000 .
0/
10
01
x2
bx 3
bx 4
x5
x6
bx 7
x8
b1000 9
0:
0;
1<
0=
0>
b0 ?
b1000 @
$end
#5000
1!
1#
0$
b0 %
1&
b0 )
0*
b0 ,
0-
1/
02
b0 3
b0 4
05
b0 7
08
1:
b0 ?
#10000
0!
0/
0:
#15000
1!
1/
1:
b0 ?
#20000
0!
0/
0:
#25000
1!
1/
1:
b0 ?
#30000
0!
0/
0:
#35000
1!
1/
1:
b0 ?
#40000
0!
0/
0:
#45000
1!
1/
1:
b0 ?
#50000
0!
0/
0:
#55000
1!
1/
1:
b0 ?
#60000
0!
0/
0:
#65000
1!
1/
1:
b0 ?
#70000
0!
0/
0:
#75000
1!
1/
1:
b0 ?
#80000
0!
0/
0:
#85000
1!
1/
1:
b0 ?
#90000
0!
0/
0:
#95000
1!
1/
1:
b0 ?
#100000
0!
0"
0/
00
11
0:
1;
0<
0=
1>
#105000
1!
b1 %
b1 ,
1/
b1 3
b1 7
1:
b0 ?
#110000
0!
0/
0:
#115000
1!
1/
b10 3
b10 7
1:
b0 ?
#120000
0!
0/
0:
#125000
1!
1/
1:
b0 ?
#130000
0!
0/
0:
#135000
1!
1/
1:
b0 ?
#140000
0!
0/
0:
#145000
1!
1/
1:
b0 ?
#150000
0!
0/
0:
#155000
1!
1/
1:
b0 ?
#160000
0!
0/
0:
#165000
1!
1/
1:
b0 ?
#170000
0!
0/
0:
#175000
1!
1/
1:
b0 ?
#180000
0!
0/
0:
#185000
1!
1/
1:
b0 ?
#190000
0!
0/
0:
#195000
1!
1/
1:
b0 ?
#200000
0!
0/
0:
0;
#205000
1!
1/
1:
b0 ?
#210000
0!
0/
0:
#215000
1!
1/
1:
b0 ?
#220000
0!
0/
0:
#225000
1!
1/
1:
b0 ?
#230000
0!
0/
0:
#235000
1!
1/
1:
b0 ?
#240000
0!
0/
0:
#245000
1!
1/
1:
b0 ?
#250000
0!
0/
0:
#255000
1!
1/
1:
b0 ?
#260000
0!
0/
0:
#265000
1!
1/
1:
b0 ?
#270000
0!
0/
0:
#275000
1!
1/
1:
b0 ?
#280000
0!
0/
0:
#285000
1!
1/
1:
b0 ?
#290000
0!
0/
0:
#295000
1!
1/
1:
b0 ?
#300000
0!
1'
0/
0:
1;
1=
1>
#305000
1!
1$
b1101 (
1-
1/
1:
b1101 ?
#310000
0!
0/
0:
#315000
1!
b1110 %
b10001101 (
b1110 ,
1/
12
18
1:
b10001101 ?
#320000
0!
0/
0:
#325000
1!
b10001110 %
b1100101 (
b10001110 ,
1/
b1111 3
b1111 7
1:
b1100101 ?
#330000
0!
0/
0:
#335000
1!
b1100110 %
b10010 (
b1100110 ,
1/
b10001111 3
b10001111 7
1:
b10010 ?
#340000
0!
0/
0:
#345000
1!
b10011 %
b1 (
b10011 ,
1/
b1100111 3
b1100111 7
1:
b1 ?
#350000
0!
0/
0:
#355000
1!
b10 %
b1101 (
b10 ,
1/
b10100 3
b10100 7
1:
b1101 ?
#360000
0!
0/
0:
#365000
1!
b1110 %
b1110110 (
b1110 ,
1/
b11 3
b11 7
1:
b1110110 ?
#370000
0!
0/
0:
#375000
1!
b1110111 %
b111101 (
b1110111 ,
1/
b1111 3
b1111 7
1:
b111101 ?
#380000
0!
0/
0:
#385000
1!
b111110 %
b11101101 (
b111110 ,
1/
b1111000 3
b1111000 7
1:
b11101101 ?
#390000
0!
0/
0:
#395000
1!
b11101110 %
b10001100 (
b11101110 ,
1/
b111111 3
b111111 7
1:
b10001100 ?
#400000
0!
0/
0:
0;
#405000
1!
b10001101 %
b11111001 (
b10001101 ,
1/
b11101111 3
b11101111 7
1:
b11111001 ?
#410000
0!
0/
0:
#415000
1!
b11111010 %
b11000110 (
b11111010 ,
1/
b10001110 3
b10001110 7
1:
b11000110 ?
#420000
0!
0/
0:
#425000
1!
b11000111 %
b11000101 (
b11000111 ,
1/
b11111011 3
b11111011 7
1:
b11000101 ?
#430000
0!
0/
0:
#435000
1!
b11000110 %
b10101010 (
b11000110 ,
1/
b11001000 3
b11001000 7
1:
b10101010 ?
#440000
0!
0/
0:
#445000
1!
b10101011 %
b11100101 (
b10101011 ,
1/
b11000111 3
b11000111 7
1:
b11100101 ?
#450000
0!
0/
0:
#455000
1!
b11100110 %
b1110111 (
b11100110 ,
1/
b10101100 3
b10101100 7
1:
b1110111 ?
#460000
0!
0/
0:
#465000
1!
b1111000 %
b10010 (
b1111000 ,
1/
b11100111 3
b11100111 7
1:
b10010 ?
#470000
0!
0/
0:
#475000
1!
b10011 %
b10001111 (
b10011 ,
1/
b1111001 3
b1111001 7
1:
b10001111 ?
#480000
0!
0/
0:
#485000
1!
b10010000 %
b11110010 (
b10010000 ,
1/
b10100 3
b10100 7
1:
b11110010 ?
#490000
0!
0/
0:
#495000
1!
b11110011 %
b11001110 (
b11110011 ,
1/
b10010001 3
b10010001 7
1:
b11001110 ?
#500000
0!
0'
0/
0:
1;
0=
1>
#505000
1!
0$
b11001111 %
b11001111 ,
0-
1/
b11110100 3
b11110100 7
1:
b11001110 ?
#510000
0!
0/
0:
#515000
1!
1/
02
b11010000 3
b11010000 7
08
1:
b11001110 ?
#520000
0!
0/
0:
#525000
1!
1/
1:
b11001110 ?
#530000
0!
0/
0:
#535000
1!
1/
1:
b11001110 ?
#540000
0!
0/
0:
#545000
1!
1/
1:
b11001110 ?
#550000
0!
0/
0:
#555000
1!
1/
1:
b11001110 ?
#560000
0!
0/
0:
#565000
1!
1/
1:
b11001110 ?
#570000
0!
0/
0:
#575000
1!
1/
1:
b11001110 ?
#580000
0!
0/
0:
#585000
1!
1/
1:
b11001110 ?
#590000
0!
0/
0:
#595000
1!
1/
1:
b11001110 ?
#600000
0!
0/
0:
0;
#605000
1!
1/
1:
b11001110 ?
#610000
0!
0/
0:
#615000
1!
1/
1:
b11001110 ?
#620000
0!
0/
0:
#625000
1!
1/
1:
b11001110 ?
#630000
0!
0/
0:
#635000
1!
1/
1:
b11001110 ?
#640000
0!
0/
0:
#645000
1!
1/
1:
b11001110 ?
#650000
0!
0/
0:
#655000
1!
1/
1:
b11001110 ?
#660000
0!
0/
0:
#665000
1!
1/
1:
b11001110 ?
#670000
0!
0/
0:
#675000
1!
1/
1:
b11001110 ?
#680000
0!
0/
0:
#685000
1!
1/
1:
b11001110 ?
#690000
0!
0/
0:
#695000
1!
1/
1:
b11001110 ?
#700000
0!
0/
0:
1;
0=
1>
#705000
1!
1/
1:
b11001110 ?
#710000
0!
0/
0:
#715000
1!
1/
1:
b11001110 ?
#720000
0!
0/
0:
#725000
1!
1/
1:
b11001110 ?
#730000
0!
0/
0:
#735000
1!
1/
1:
b11001110 ?
#740000
0!
0/
0:
#745000
1!
1/
1:
b11001110 ?
#750000
0!
0/
0:
#755000
1!
1/
1:
b11001110 ?
#760000
0!
0/
0:
#765000
1!
1/
1:
b11001110 ?
#770000
0!
0/
0:
#775000
1!
1/
1:
b11001110 ?
#780000
0!
0/
0:
#785000
1!
1/
1:
b11001110 ?
#790000
0!
0/
0:
#795000
1!
1/
1:
b11001110 ?
#800000
0!
0/
0:
0;
#805000
1!
1/
1:
b11001110 ?
#810000
0!
0/
0:
#815000
1!
1/
1:
b11001110 ?
#820000
0!
0/
0:
#825000
1!
1/
1:
b11001110 ?
#830000
0!
0/
0:
#835000
1!
1/
1:
b11001110 ?
#840000
0!
0/
0:
#845000
1!
1/
1:
b11001110 ?
#850000
0!
0/
0:
#855000
1!
1/
1:
b11001110 ?
#860000
0!
0/
0:
#865000
1!
1/
1:
b11001110 ?
#870000
0!
0/
0:
#875000
1!
1/
1:
b11001110 ?
#880000
0!
0/
0:
#885000
1!
1/
1:
b11001110 ?
#890000
0!
0/
0:
#895000
1!
1/
1:
b11001110 ?
#900000
0!
1'
0/
0:
1;
1=
1>
#905000
1!
1$
b1100011 (
1-
1/
1:
b1100011 ?
#910000
0!
0/
0:
#915000
1!
b1100100 %
b1010 (
b1100100 ,
1/
12
18
1:
b1010 ?
#920000
0!
0/
0:
#925000
1!
b1011 %
b10000000 (
b1011 ,
1/
b1100101 3
b1100101 7
1:
b10000000 ?
#930000
0!
0/
0:
#935000
1!
b10000001 %
b100000 (
b10000001 ,
1/
b1100 3
b1100 7
1:
b100000 ?
#940000
0!
0/
0:
#945000
1!
b100001 %
b10101010 (
b100001 ,
1/
b10000010 3
b10000010 7
1:
b10101010 ?
#950000
0!
0/
0:
#955000
1!
b10101011 %
b10011101 (
b10101011 ,
1/
b100010 3
b100010 7
1:
b10011101 ?
#960000
0!
0/
0:
#965000
1!
b10011110 %
b10010110 (
b10011110 ,
1/
b10101100 3
b10101100 7
1:
b10010110 ?
#970000
0!
0/
0:
#975000
1!
b10010111 %
b10011 (
b10010111 ,
1/
b10011111 3
b10011111 7
1:
b10011 ?
#980000
0!
0/
0:
#985000
1!
b10100 %
b1101 (
b10100 ,
1/
b10011000 3
b10011000 7
1:
b1101 ?
#990000
0!
0/
0:
#995000
1!
b1110 %
b1010011 (
b1110 ,
1/
b10101 3
b10101 7
1:
b1010011 ?
#1000000
0!
0/
0:
0;
#1005000
1!
b1010100 %
b1101011 (
b1010100 ,
1/
b1111 3
b1111 7
1:
b1101011 ?
#1010000
0!
0/
0:
#1015000
1!
b1101100 %
b11010101 (
b1101100 ,
1/
b1010101 3
b1010101 7
1:
b11010101 ?
#1020000
0!
0/
0:
#1025000
1!
b11010110 %
b10 (
b11010110 ,
1/
b1101101 3
b1101101 7
1:
b10 ?
#1030000
0!
0/
0:
#1035000
1!
b11 %
b10101110 (
b11 ,
1/
b11010111 3
b11010111 7
1:
b10101110 ?
#1040000
0!
0/
0:
#1045000
1!
b10101111 %
b11101 (
b10101111 ,
1/
b100 3
b100 7
1:
b11101 ?
#1050000
0!
0/
0:
#1055000
1!
b11110 %
b11001111 (
b11110 ,
1/
b10110000 3
b10110000 7
1:
b11001111 ?
#1060000
0!
0/
0:
#1065000
1!
b11010000 %
b100011 (
b11010000 ,
1/
b11111 3
b11111 7
1:
b100011 ?
#1070000
0!
0/
0:
#1075000
1!
b100100 %
b1010 (
b100100 ,
1/
b11010001 3
b11010001 7
1:
b1010 ?
#1080000
0!
0/
0:
#1085000
1!
b1011 %
b11001010 (
b1011 ,
1/
b100101 3
b100101 7
1:
b11001010 ?
#1090000
0!
0/
0:
#1095000
1!
b11001011 %
b111100 (
b11001011 ,
1/
b1100 3
b1100 7
1:
b111100 ?
#1100000
0!
0'
0/
01
0:
1;
0=
0>
#1105000
1!
0#
0$
b111101 %
b111101 ,
0-
1/
b1100 4
15
b11001100 7
1:
b111100 ?
#1110000
0!
0/
0:
#1115000
1!
b111101 )
1/
1:
b111100 ?
#1120000
0!
0/
0:
#1125000
1!
1/
1:
b111100 ?
#1130000
0!
0/
0:
#1135000
1!
1/
1:
b111100 ?
#1140000
0!
0/
0:
#1145000
1!
1/
1:
b111100 ?
#1150000
0!
0/
0:
#1155000
1!
1/
1:
b111100 ?
#1160000
0!
0/
0:
#1165000
1!
1/
1:
b111100 ?
#1170000
0!
0/
0:
#1175000
1!
1/
1:
b111100 ?
#1180000
0!
0/
0:
#1185000
1!
1/
1:
b111100 ?
#1190000
0!
0/
0:
#1195000
1!
1/
1:
b111100 ?
#1200000
0!
0/
0:
0;
#1205000
1!
1/
1:
b111100 ?
#1210000
0!
0/
0:
#1215000
1!
1/
1:
b111100 ?
#1220000
0!
0/
0:
#1225000
1!
1/
1:
b111100 ?
#1230000
0!
0/
0:
#1235000
1!
1/
1:
b111100 ?
#1240000
0!
0/
0:
#1245000
1!
1/
1:
b111100 ?
#1250000
0!
0/
0:
#1255000
1!
1/
1:
b111100 ?
#1260000
0!
0/
0:
#1265000
1!
1/
1:
b111100 ?
#1270000
0!
0/
0:
#1275000
1!
1/
1:
b111100 ?
#1280000
0!
0/
0:
#1285000
1!
1/
1:
b111100 ?
#1290000
0!
0/
0:
#1295000
1!
1/
1:
b111100 ?
#1300000
0!
1'
0/
0:
1;
1=
0>
#1305000
1!
1$
b1111000 (
1-
1/
1:
b1111000 ?
#1310000
0!
0/
0:
#1315000
1!
0&
b10001001 (
1*
b1111001 ,
1/
1:
b10001001 ?
#1320000
0!
0/
0:
#1325000
1!
1/
1:
b10001001 ?
#1330000
0!
0/
0:
#1335000
1!
1/
1:
b10001001 ?
#1340000
0!
0/
0:
#1345000
1!
1/
1:
b10001001 ?
#1350000
0!
0/
0:
#1355000
1!
1/
1:
b10001001 ?
#1360000
0!
0/
0:
#1365000
1!
1/
1:
b10001001 ?
#1370000
0!
0/
0:
#1375000
1!
1/
1:
b10001001 ?
#1380000
0!
0/
0:
#1385000
1!
1/
1:
b10001001 ?
#1390000
0!
0/
0:
#1395000
1!
1/
1:
b10001001 ?
#1400000
0!
0/
0:
0;
#1405000
1!
1/
1:
b10001001 ?
#1410000
0!
0/
0:
#1415000
1!
1/
1:
b10001001 ?
#1420000
0!
0/
0:
#1425000
1!
1/
1:
b10001001 ?
#1430000
0!
0/
0:
#1435000
1!
1/
1:
b10001001 ?
#1440000
0!
0/
0:
#1445000
1!
1/
1:
b10001001 ?
#1450000
0!
0/
0:
#1455000
1!
1/
1:
b10001001 ?
#1460000
0!
0/
0:
#1465000
1!
1/
1:
b10001001 ?
#1470000
0!
0/
0:
#1475000
1!
1/
1:
b10001001 ?
#1480000
0!
0/
0:
#1485000
1!
1/
1:
b10001001 ?
#1490000
0!
0/
0:
#1495000
1!
1/
1:
b10001001 ?
#1500000
0!
0/
0:
1;
1=
0>
#1505000
1!
1/
1:
b10001001 ?
#1510000
0!
0/
0:
#1515000
1!
1/
1:
b10001001 ?
#1520000
0!
0/
0:
#1525000
1!
1/
1:
b10001001 ?
#1530000
0!
0/
0:
#1535000
1!
1/
1:
b10001001 ?
#1540000
0!
0/
0:
#1545000
1!
1/
1:
b10001001 ?
#1550000
0!
0/
0:
#1555000
1!
1/
1:
b10001001 ?
#1560000
0!
0/
0:
#1565000
1!
1/
1:
b10001001 ?
#1570000
0!
0/
0:
#1575000
1!
1/
1:
b10001001 ?
#1580000
0!
0/
0:
#1585000
1!
1/
1:
b10001001 ?
#1590000
0!
0/
0:
#1595000
1!
1/
1:
b10001001 ?
#1600000
0!
0/
0:
0;
#1605000
1!
1/
1:
b10001001 ?
#1610000
0!
0/
0:
#1615000
1!
1/
1:
b10001001 ?
#1620000
0!
0/
0:
#1625000
1!
1/
1:
b10001001 ?
#1630000
0!
0/
0:
#1635000
1!
1/
1:
b10001001 ?
#1640000
0!
0/
0:
#1645000
1!
1/
1:
b10001001 ?
#1650000
0!
0/
0:
#1655000
1!
1/
1:
b10001001 ?
#1660000
0!
0/
0:
#1665000
1!
1/
1:
b10001001 ?
#1670000
0!
0/
0:
#1675000
1!
1/
1:
b10001001 ?
#1680000
0!
0/
0:
#1685000
1!
1/
1:
b10001001 ?
#1690000
0!
0/
0:
#1695000
1!
1/
1:
b10001001 ?
#1700000
0!
0'
0/
0:
1;
0=
0>
#1705000
1!
1/
1:
b10001001 ?
#1710000
0!
0/
0:
#1715000
1!
1/
1:
b10001001 ?
#1720000
0!
0/
0:
#1725000
1!
1/
1:
b10001001 ?
#1730000
0!
0/
0:
#1735000
1!
1/
1:
b10001001 ?
#1740000
0!
0/
0:
#1745000
1!
1/
1:
b10001001 ?
#1750000
0!
0/
0:
#1755000
1!
1/
1:
b10001001 ?
#1760000
0!
0/
0:
#1765000
1!
1/
1:
b10001001 ?
#1770000
0!
0/
0:
#1775000
1!
1/
1:
b10001001 ?
#1780000
0!
0/
0:
#1785000
1!
1/
1:
b10001001 ?
#1790000
0!
0/
0:
#1795000
1!
1/
1:
b10001001 ?
#1800000
0!
0/
0:
0;
#1805000
1!
1/
1:
b10001001 ?
#1810000
0!
0/
0:
#1815000
1!
1/
1:
b10001001 ?
#1820000
0!
0/
0:
#1825000
1!
1/
1:
b10001001 ?
#1830000
0!
0/
0:
#1835000
1!
1/
1:
b10001001 ?
#1840000
0!
0/
0:
#1845000
1!
1/
1:
b10001001 ?
#1850000
0!
0/
0:
#1855000
1!
1/
1:
b10001001 ?
#1860000
0!
0/
0:
#1865000
1!
1/
1:
b10001001 ?
#1870000
0!
0/
0:
#1875000
1!
1/
1:
b10001001 ?
#1880000
0!
0/
0:
#1885000
1!
1/
1:
b10001001 ?
#1890000
0!
0/
0:
#1895000
1!
1/
1:
b10001001 ?
#1900000
0!
0/
0:
1;
0=
0>
#1905000
1!
1/
1:
b10001001 ?
#1910000
0!
0/
0:
#1915000
1!
1/
1:
b10001001 ?
#1920000
0!
0/
0:
#1925000
1!
1/
1:
b10001001 ?
#1930000
0!
0/
0:
#1935000
1!
1/
1:
b10001001 ?
#1940000
0!
0/
0:
#1945000
1!
1/
1:
b10001001 ?
#1950000
0!
0/
0:
#1955000
1!
1/
1:
b10001001 ?
#1960000
0!
0/
0:
#1965000
1!
1/
1:
b10001001 ?
#1970000
0!
0/
0:
#1975000
1!
1/
1:
b10001001 ?
#1980000
0!
0/
0:
#1985000
1!
1/
1:
b10001001 ?
#1990000
0!
0/
0:
#1995000
1!
1/
1:
b10001001 ?
#2000000
0!
0/
0:
0;
#2005000
1!
1/
1:
b10001001 ?
#2010000
0!
0/
0:
#2015000
1!
1/
1:
b10001001 ?
#2020000
0!
0/
0:
#2025000
1!
1/
1:
b10001001 ?
#2030000
0!
0/
0:
#2035000
1!
1/
1:
b10001001 ?
#2040000
0!
0/
0:
#2045000
1!
1/
1:
b10001001 ?
#2050000
0!
0/
0:
#2055000
1!
1/
1:
b10001001 ?
#2060000
0!
0/
0:
#2065000
1!
1/
1:
b10001001 ?
#2070000
0!
0/
0:
#2075000
1!
1/
1:
b10001001 ?
#2080000
0!
0/
0:
#2085000
1!
1/
1:
b10001001 ?
#2090000
0!
0/
0:
#2095000
1!
1/
1:
b10001001 ?
#2100000
0!
1'
0/
11
0:
1;
1=
1>
#2105000
1!
1#
1/
b11001100 3
05
1:
b10001001 ?
#2110000
0!
0/
0:
#2115000
1!
b1111001 %
1&
0*
1/
b111110 3
b111110 7
1:
b10001001 ?
#2120000
0!
0/
0:
#2125000
1!
b10001010 %
b10000101 (
b10001010 ,
1/
b1111010 3
b1111010 7
1:
b10000101 ?
#2130000
0!
0/
0:
#2135000
1!
b10000110 %
b1001111 (
b10000110 ,
1/
b10001011 3
b10001011 7
1:
b1001111 ?
#2140000
0!
0/
0:
#2145000
1!
b1010000 %
b111011 (
b1010000 ,
1/
b10000111 3
b10000111 7
1:
b111011 ?
#2150000
0!
0/
0:
#2155000
1!
b111100 %
b111010 (
b111100 ,
1/
b1010001 3
b1010001 7
1:
b111010 ?
#2160000
0!
0/
0:
#2165000
1!
b111011 %
b1111110 (
b111011 ,
1/
b111101 3
b111101 7
1:
b1111110 ?
#2170000
0!
0/
0:
#2175000
1!
b1111111 %
b10101 (
b1111111 ,
1/
b111100 3
b111100 7
1:
b10101 ?
#2180000
0!
0/
0:
#2185000
1!
b10110 %
b11110001 (
b10110 ,
1/
b10000000 3
b10000000 7
1:
b11110001 ?
#2190000
0!
0/
0:
#2195000
1!
b11110010 %
b11011001 (
b11110010 ,
1/
b10111 3
b10111 7
1:
b11011001 ?
#2200000
0!
0/
0:
0;
#2205000
1!
b11011010 %
b1100010 (
b11011010 ,
1/
b11110011 3
b11110011 7
1:
b1100010 ?
#2210000
0!
0/
0:
#2215000
1!
b1100011 %
b1001100 (
b1100011 ,
1/
b11011011 3
b11011011 7
1:
b1001100 ?
#2220000
0!
0/
0:
#2225000
1!
b1001101 %
b10011111 (
b1001101 ,
1/
b1100100 3
b1100100 7
1:
b10011111 ?
#2230000
0!
0/
0:
#2235000
1!
b10100000 %
b10001111 (
b10100000 ,
1/
b1001110 3
b1001110 7
1:
b10001111 ?
#2240000
0!
0/
0:
#2245000
1!
b10010000 %
b11111000 (
b10010000 ,
1/
b10100001 3
b10100001 7
1:
b11111000 ?
#2250000
0!
0/
0:
#2255000
1!
b11111001 %
b10110111 (
b11111001 ,
1/
b10010001 3
b10010001 7
1:
b10110111 ?
#2260000
0!
0/
0:
#2265000
1!
b10111000 %
b10011111 (
b10111000 ,
1/
b11111010 3
b11111010 7
1:
b10011111 ?
#2270000
0!
0/
0:
#2275000
1!
b10100000 %
b1011100 (
b10100000 ,
1/
b10111001 3
b10111001 7
1:
b1011100 ?
#2280000
0!
0/
0:
#2285000
1!
b1011101 %
b1011011 (
b1011101 ,
1/
b10100001 3
b10100001 7
1:
b1011011 ?
#2290000
0!
0/
0:
#2295000
1!
b1011100 %
b10001001 (
b1011100 ,
1/
b1011110 3
b1011110 7
1:
b10001001 ?
#2300000
0!
0/
01
0:
1;
1=
0>
#2305000
1!
0#
b10001010 %
b11010111 (
b10001010 ,
1/
b1011110 4
15
b1011101 7
1:
b11010111 ?
#2310000
0!
0/
0:
#2315000
1!
0&
b1010001 (
b10001010 )
1*
b11011000 ,
1/
1:
b1010001 ?
#2320000
0!
0/
0:
#2325000
1!
1/
1:
b1010001 ?
#2330000
0!
0/
0:
#2335000
1!
1/
1:
b1010001 ?
#2340000
0!
0/
0:
#2345000
1!
1/
1:
b1010001 ?
#2350000
0!
0/
0:
#2355000
1!
1/
1:
b1010001 ?
#2360000
0!
0/
0:
#2365000
1!
1/
1:
b1010001 ?
#2370000
0!
0/
0:
#2375000
1!
1/
1:
b1010001 ?
#2380000
0!
0/
0:
#2385000
1!
1/
1:
b1010001 ?
#2390000
0!
0/
0:
#2395000
1!
1/
1:
b1010001 ?
#2400000
0!
0/
0:
0;
#2405000
1!
1/
1:
b1010001 ?
#2410000
0!
0/
0:
#2415000
1!
1/
1:
b1010001 ?
#2420000
0!
0/
0:
#2425000
1!
1/
1:
b1010001 ?
#2430000
0!
0/
0:
#2435000
1!
1/
1:
b1010001 ?
#2440000
0!
0/
0:
#2445000
1!
1/
1:
b1010001 ?
#2450000
0!
0/
0:
#2455000
1!
1/
1:
b1010001 ?
#2460000
0!
0/
0:
#2465000
1!
1/
1:
b1010001 ?
#2470000
0!
0/
0:
#2475000
1!
1/
1:
b1010001 ?
#2480000
0!
0/
0:
#2485000
1!
1/
1:
b1010001 ?
#2490000
0!
0/
0:
#2495000
1!
1/
1:
b1010001 ?
#2500000
0!
0'
0/
0:
1;
0=
0>
#2505000
1!
1/
1:
b1010001 ?
#2510000
0!
0/
0:
#2515000
1!
1/
1:
b1010001 ?
#2520000
0!
0/
0:
#2525000
1!
1/
1:
b1010001 ?
#2530000
0!
0/
0:
#2535000
1!
1/
1:
b1010001 ?
#2540000
0!
0/
0:
#2545000
1!
1/
1:
b1010001 ?
#2550000
0!
0/
0:
#2555000
1!
1/
1:
b1010001 ?
#2560000
0!
0/
0:
#2565000
1!
1/
1:
b1010001 ?
#2570000
0!
0/
0:
#2575000
1!
1/
1:
b1010001 ?
#2580000
0!
0/
0:
#2585000
1!
1/
1:
b1010001 ?
#2590000
0!
0/
0:
#2595000
1!
1/
1:
b1010001 ?
#2600000
0!
0/
0:
0;
#2605000
1!
1/
1:
b1010001 ?
#2610000
0!
0/
0:
#2615000
1!
1/
1:
b1010001 ?
#2620000
0!
0/
0:
#2625000
1!
1/
1:
b1010001 ?
#2630000
0!
0/
0:
#2635000
1!
1/
1:
b1010001 ?
#2640000
0!
0/
0:
#2645000
1!
1/
1:
b1010001 ?
#2650000
0!
0/
0:
#2655000
1!
1/
1:
b1010001 ?
#2660000
0!
0/
0:
#2665000
1!
1/
1:
b1010001 ?
#2670000
0!
0/
0:
#2675000
1!
1/
1:
b1010001 ?
#2680000
0!
0/
0:
#2685000
1!
1/
1:
b1010001 ?
#2690000
0!
0/
0:
#2695000
1!
1/
1:
b1010001 ?
#2700000
0!
0/
0:
1;
0=
0>
#2705000
1!
1/
1:
b1010001 ?
#2710000
0!
0/
0:
#2715000
1!
1/
1:
b1010001 ?
#2720000
0!
0/
0:
#2725000
1!
1/
1:
b1010001 ?
#2730000
0!
0/
0:
#2735000
1!
1/
1:
b1010001 ?
#2740000
0!
0/
0:
#2745000
1!
1/
1:
b1010001 ?
#2750000
0!
0/
0:
#2755000
1!
1/
1:
b1010001 ?
#2760000
0!
0/
0:
#2765000
1!
1/
1:
b1010001 ?
#2770000
0!
0/
0:
#2775000
1!
1/
1:
b1010001 ?
#2780000
0!
0/
0:
#2785000
1!
1/
1:
b1010001 ?
#2790000
0!
0/
0:
#2795000
1!
1/
1:
b1010001 ?
#2800000
0!
0/
0:
0;
#2805000
1!
1/
1:
b1010001 ?
#2810000
0!
0/
0:
