src/axi_module_all.v
//////////////////////////////////////////////////////////////////////////////////
// Engineer:
// 
// Create Date: 2022/11/13 16:16:32
// Design Name: 
// Module Name: 
// Description: 
// 
// Dependencies: 
// 
// Revision:
// Revision 0.01 - File Created
// Additional Comments:
// valid和ready都需要打拍的代码

`timescale  1ns/1ps

// 将前面2种情况结合起来
// 似乎axi_module就是对valid打一拍的情况了，毕竟题目原本就没说模块内要啥操作
// 同样，可以用valid_i和ready_i
module axi_module_all #(
    parameter DWIDTH = 8
)
(
    input                   aclk_i,
    input                   areset_i,

    // down-stream
    input                   ready_i,
    output reg              valid_o = 'd0,
    output reg [DWIDTH-1:0] data_o = 'd0,

    // up-stream
    output                  ready_o,
    input                   valid_i,
    input  [DWIDTH-1:0]     data_i   
);

wire input_trig, output_trig;
reg  valid_i_reg, ready_i_reg;
reg  [DWIDTH-1:0] data_i_reg;
reg  [DWIDTH-1:0] data_temp;
reg  ready_flag;

assign input_trig   = ready_o & valid_i_reg;
assign output_trig  = ready_i & valid_o;

assign ready_o = ~valid_o | ready_i_reg;



always @(posedge aclk_i) begin
    valid_i_reg <= valid_i;
    ready_i_reg <= ready_i;
end

always @(posedge aclk_i) begin
    // 这里可以添加其他运算，尽量将此1个时钟周期的延时利用起来
    if(ready_o)
        data_i_reg <= data_i + 1'b1;
    else 
        data_i_reg <= data_i_reg;
end

always @(posedge aclk_i) begin
    if(input_trig && ~ready_i) begin
        ready_flag  <= 1'b1;
        data_temp   <= data_i;
    end
    else if(ready_i) begin
        ready_flag  <= 1'b0;
        data_temp   <= 'd0;
    end
end



always @(posedge aclk_i) begin
    if(input_trig && ready_i) begin
        valid_o <= 1'b1;
        data_o  <= data_i_reg + 1'b1;            
    end
    else if(input_trig && ~ready_i) begin
        data_o  <= data_o;
        valid_o <= valid_o;
    end
    else if(~ready_i_reg && ready_i) begin
        if(ready_flag) begin
            data_o  <= data_temp + 1'b1;
            valid_o <= 1'b1;
        end
        else begin
            data_o  <= data_i_reg + 1'b1;
            valid_o <= 1'b1;
        end
    end
    else if(~valid_i)begin
        valid_o <= 1'b0;
        data_o  <= data_o;
    end
end



endmodule

tb/tb.v
`timescale 1ns/1ps

module tb();

localparam DWIDTH = 8;

reg aclk = 'd0;
reg areset = 'd0;
wire up_ready, up_valid;
wire down_ready, down_valid;
wire last_ready, last_valid;
reg [DWIDTH-1:0] up_data = 'd0; 
wire[DWIDTH-1:0] down_data, last_data;

always #5 aclk = ~aclk;

// 产生随机数据
always @(posedge aclk) begin
    if(up_ready == 1'b1 && up_valid)
        up_data <= $random();
    else
        up_data <= up_data;
end

initial begin
    #10
    // 连续传输情况，无气泡
    force up_valid = 'd1;
    force last_ready = 'd1;
    if(up_ready == 1'b0)
        $display("Error! Must transfer continuously!");
    #200

    // 无有效数据传输情况
    force up_valid = 'd0;
    #100
    force up_valid = 'd1;
    #100

    // 反压情况
    force last_ready = 'd0;
    #100
    force last_ready = 'd1;
    #100


    $finish;
end


axi_module_all #(.DWIDTH(DWIDTH)) master
(
    .aclk_i     (aclk),
    .areset_i   (areset),
    .ready_i    (down_ready),
    .valid_o    (down_valid),
    .data_o     (down_data),
    .ready_o    (up_ready),
    .valid_i    (up_valid),
    .data_i     (up_data)  
);

axi_module_all #(.DWIDTH(DWIDTH)) slave
(
    .aclk_i     (aclk),
    .areset_i   (areset),
    .ready_i    (last_ready),
    .valid_o    (last_valid),
    .data_o     (last_data),
    .ready_o    (down_ready),
    .valid_i    (down_valid),
    .data_i     (down_data)  
);



endmodule

vcd/axi_module_all.vcd
$date
   Mon Nov 14 17:20:16 2022
$end
$version
  2020.2
$end
$timescale
  1ps
$end
$scope module tb $end
$var reg 1 @ aclk $end
$var reg 1 A areset $end
$var wire 1 & up_ready $end
$var wire 1 ' up_valid $end
$var wire 1 # down_ready $end
$var wire 1 6 down_valid $end
$var wire 1 3 last_ready $end
$var wire 1 B last_valid $end
$var reg 8 C up_data [7:0] $end
$var wire 8 7 down_data [7:0] $end
$var wire 8 D last_data [7:0] $end
$var parameter 32 E DWIDTH [31:0] $end
$scope module master $end
$var wire 1 ! aclk_i $end
$var wire 1 " areset_i $end
$var wire 1 # ready_i $end
$var reg 1 $ valid_o $end
$var reg 8 % data_o [7:0] $end
$var wire 1 & ready_o $end
$var wire 1 ' valid_i $end
$var wire 8 ( data_i [7:0] $end
$var wire 1 ) input_trig $end
$var wire 1 * output_trig $end
$var reg 1 + valid_i_reg $end
$var reg 1 , ready_i_reg $end
$var reg 8 - data_i_reg [7:0] $end
$var reg 8 . data_temp [7:0] $end
$var reg 1 / ready_flag $end
$var parameter 32 0 DWIDTH [31:0] $end
$upscope $end
$scope module slave $end
$var wire 1 1 aclk_i $end
$var wire 1 2 areset_i $end
$var wire 1 3 ready_i $end
$var reg 1 4 valid_o $end
$var reg 8 5 data_o [7:0] $end
$var wire 1 # ready_o $end
$var wire 1 6 valid_i $end
$var wire 8 7 data_i [7:0] $end
$var wire 1 8 input_trig $end
$var wire 1 9 output_trig $end
$var reg 1 : valid_i_reg $end
$var reg 1 ; ready_i_reg $end
$var reg 8 < data_i_reg [7:0] $end
$var reg 8 = data_temp [7:0] $end
$var reg 1 > ready_flag $end
$var parameter 32 ? DWIDTH [31:0] $end
$upscope $end
$upscope $end
$enddefinitions $end
#0
$dumpvars
0!
0"
1#
0$
b0 %
1&
z'
b0 (
x)
0*
x+
x,
bx -
bx .
x/
b1000 0
01
02
z3
04
b0 5
06
b0 7
x8
09
x:
x;
bx <
bx =
x>
b1000 ?
0@
0A
0B
b0 C
b0 D
b1000 E
$end
#5000
1!
1#
1&
z+
1,
b1 -
b0 .
0/
11
04
b0 5
08
0:
z;
b1 <
1@
b0 C
#10000
0!
1'
01
13
0@
#15000
1!
1#
b100100 (
1)
1+
11
04
b0 5
1;
b0 =
0>
1@
b100100 C
#20000
0!
01
0@
#25000
1!
1$
b10 %
1&
b10000001 (
1*
b100101 -
11
04
b0 5
16
b10 7
1@
b10000001 C
#30000
0!
01
0@
#35000
1!
1$
b100110 %
b1001 (
b10000010 -
11
b100110 7
18
1:
b11 <
1@
b1001 C
#40000
0!
01
0@
#45000
1!
1#
1$
b10000011 %
b1100011 (
b1010 -
11
14
b100 5
b10000011 7
19
b100111 <
1@
1B
b1100011 C
b100 D
#50000
0!
01
0@
#55000
1!
1$
b1011 %
b1101 (
b1100100 -
11
14
b101000 5
b1011 7
b10000100 <
1@
b1101 C
b101000 D
#60000
0!
01
0@
#65000
1!
1$
b1100101 %
b10001101 (
b1110 -
11
14
b10000101 5
b1100101 7
b1100 <
1@
b10001101 C
b10000101 D
#70000
0!
01
0@
#75000
1!
1$
b1111 %
b1100101 (
b10001110 -
11
14
b1101 5
b1111 7
b1100110 <
1@
b1100101 C
b1101 D
#80000
0!
01
0@
#85000
1!
1$
b10001111 %
b10010 (
b1100110 -
11
14
b1100111 5
b10001111 7
b10000 <
1@
b10010 C
b1100111 D
#90000
0!
01
0@
#95000
1!
1$
b1100111 %
b1 (
b10011 -
11
14
b10001 5
b1100111 7
b10010000 <
1@
b1 C
b10001 D
#100000
0!
01
0@
#105000
1!
1$
b10100 %
b1101 (
b10 -
11
14
b10010001 5
b10100 7
b1101000 <
1@
b1101 C
b10010001 D
#110000
0!
01
0@
#115000
1!
1$
b11 %
b1110110 (
b1110 -
11
14
b1101001 5
b11 7
b10101 <
1@
b1110110 C
b1101001 D
#120000
0!
01
0@
#125000
1!
1$
b1111 %
b111101 (
b1110111 -
11
14
b10110 5
b1111 7
b100 <
1@
b111101 C
b10110 D
#130000
0!
01
0@
#135000
1!
1$
b1111000 %
b11101101 (
b111110 -
11
14
b101 5
b1111000 7
b10000 <
1@
b11101101 C
b101 D
#140000
0!
01
0@
#145000
1!
1$
b111111 %
b10001100 (
b11101110 -
11
14
b10001 5
b111111 7
b1111001 <
1@
b10001100 C
b10001 D
#150000
0!
01
0@
#155000
1!
1$
b11101111 %
b11111001 (
b10001101 -
11
14
b1111010 5
b11101111 7
b1000000 <
1@
b11111001 C
b1111010 D
#160000
0!
01
0@
#165000
1!
1$
b10001110 %
b11000110 (
b11111010 -
11
14
b1000001 5
b10001110 7
b11110000 <
1@
b11000110 C
b1000001 D
#170000
0!
01
0@
#175000
1!
1$
b11111011 %
b11000101 (
b11000111 -
11
14
b11110001 5
b11111011 7
b10001111 <
1@
b11000101 C
b11110001 D
#180000
0!
01
0@
#185000
1!
1$
b11001000 %
b10101010 (
b11000110 -
11
14
b10010000 5
b11001000 7
b11111100 <
1@
b10101010 C
b10010000 D
#190000
0!
01
0@
#195000
1!
1$
b11000111 %
b11100101 (
b10101011 -
11
14
b11111101 5
b11000111 7
b11001001 <
1@
b11100101 C
b11111101 D
#200000
0!
01
0@
#205000
1!
1$
b10101100 %
b1110111 (
b11100110 -
11
14
b11001010 5
b10101100 7
b11001000 <
1@
b1110111 C
b11001010 D
#210000
0!
0'
01
0@
#215000
1!
1$
b11100111 %
0)
0+
b1111000 -
11
14
b11001001 5
b11100111 7
b10101101 <
1@
b1110111 C
b11001001 D
#220000
0!
01
0@
#225000
1!
0$
b11100111 %
1&
0*
11
14
b10101110 5
06
b11101000 <
1@
b1110111 C
b10101110 D
#230000
0!
01
0@
#235000
1!
0$
b11100111 %
11
14
b11101001 5
08
0:
1@
b1110111 C
b11101001 D
#240000
0!
01
0@
#245000
1!
1#
0$
b11100111 %
11
04
b11101001 5
09
1@
0B
b1110111 C
#250000
0!
01
0@
#255000
1!
0$
b11100111 %
11
04
b11101001 5
1@
b1110111 C
#260000
0!
01
0@
#265000
1!
0$
b11100111 %
11
04
b11101001 5
1@
b1110111 C
#270000
0!
01
0@
#275000
1!
0$
b11100111 %
11
04
b11101001 5
1@
b1110111 C
#280000
0!
01
0@
#285000
1!
0$
b11100111 %
11
04
b11101001 5
1@
b1110111 C
#290000
0!
01
0@
#295000
1!
0$
b11100111 %
11
04
b11101001 5
1@
b1110111 C
#300000
0!
01
0@
#305000
1!
0$
b11100111 %
11
04
b11101001 5
1@
b1110111 C
#310000
0!
1'
01
0@
#315000
1!
b10010 (
1)
1+
11
04
b11101001 5
1@
b10010 C
#320000
0!
01
0@
#325000
1!
1$
b1111001 %
1&
b10001111 (
1*
b10011 -
11
04
b11101001 5
16
b1111001 7
1@
b10001111 C
#330000
0!
01
0@
#335000
1!
1$
b10100 %
b11110010 (
b10010000 -
11
b10100 7
18
1:
b1111010 <
1@
b11110010 C
#340000
0!
01
0@
#345000
1!
1#
1$
b10010001 %
b11001110 (
b11110011 -
11
14
b1111011 5
b10010001 7
19
b10101 <
1@
1B
b11001110 C
b1111011 D
#350000
0!
01
0@
#355000
1!
1$
b11110100 %
b11101000 (
b11001111 -
11
14
b10110 5
b11110100 7
b10010010 <
1@
b11101000 C
b10110 D
#360000
0!
01
0@
#365000
1!
1$
b11010000 %
b11000101 (
b11101001 -
11
14
b10010011 5
b11010000 7
b11110101 <
1@
b11000101 C
b10010011 D
#370000
0!
01
0@
#375000
1!
1$
b11101010 %
b1011100 (
b11000110 -
11
14
b11110110 5
b11101010 7
b11010001 <
1@
b1011100 C
b11110110 D
#380000
0!
01
0@
#385000
1!
1$
b11000111 %
b10111101 (
b1011101 -
11
14
b11010010 5
b11000111 7
b11101011 <
1@
b10111101 C
b11010010 D
#390000
0!
01
0@
#395000
1!
1$
b1011110 %
b101101 (
b10111110 -
11
14
b11101100 5
b1011110 7
b11001000 <
1@
b101101 C
b11101100 D
#400000
0!
01
0@
#405000
1!
1$
b10111111 %
b1100101 (
b101110 -
11
14
b11001001 5
b10111111 7
b1011111 <
1@
b1100101 C
b11001001 D
#410000
0!
01
03
09
0@
#415000
1!
0#
1$
b101111 %
b1100011 (
0*
b1100110 -
11
14
b11001001 5
b101111 7
08
0;
b11000000 <
b10111111 =
1>
1@
b1100011 C
#420000
0!
01
0@
#425000
1!
1$
b101111 %
0&
b1010 (
0)
0,
b1100100 -
b1100011 .
1/
11
1@
b1010 C
#430000
0!
01
0@
#435000
1!
11
1@
b1010 C
#440000
0!
01
0@
#445000
1!
11
1@
b1010 C
#450000
0!
01
0@
#455000
1!
11
1@
b1010 C
#460000
0!
01
0@
#465000
1!
11
1@
b1010 C
#470000
0!
01
0@
#475000
1!
11
1@
b1010 C
#480000
0!
01
0@
#485000
1!
11
1@
b1010 C
#490000
0!
01
0@
#495000
1!
11
1@
b1010 C
#500000
0!
01
0@
#505000
1!
11
1@
b1010 C
#510000
0!
01
13
19
0@
#515000
1!
1#
1*
11
14
b11000000 5
18
1;
b0 =
0>
1@
b1010 C
b11000000 D
#520000
0!
01
0@
#525000
1!
1$
b1100100 %
1&
1)
1,
b0 .
0/
11
14
b11000001 5
b1100100 7
b110000 <
1@
b1010 C
b11000001 D
#530000
0!
01
0@
#535000
1!
1$
b1100101 %
b10000000 (
b1011 -
11
14
b110001 5
b1100101 7
b1100101 <
1@
b10000000 C
b110001 D
#540000
0!
01
0@
#545000
1!
1$
b1100 %
b100000 (
b10000001 -
11
14
b1100110 5
b1100 7
b1100110 <
1@
b100000 C
b1100110 D
#550000
0!
01
0@
#555000
1!
1$
b10000010 %
b10101010 (
b100001 -
11
14
b1100111 5
b10000010 7
b1101 <
1@
b10101010 C
b1100111 D
#560000
0!
01
0@
#565000
1!
1$
b100010 %
b10011101 (
b10101011 -
11
14
b1110 5
b100010 7
b10000011 <
1@
b10011101 C
b1110 D
#570000
0!
01
0@
#575000
1!
1$
b10101100 %
b10010110 (
b10011110 -
11
14
b10000100 5
b10101100 7
b100011 <
1@
b10010110 C
b10000100 D
#580000
0!
01
0@
#585000
1!
1$
b10011111 %
b10011 (
b10010111 -
11
14
b100100 5
b10011111 7
b10101101 <
1@
b10011 C
b100100 D
#590000
0!
01
0@
#595000
1!
1$
b10011000 %
b1101 (
b10100 -
11
14
b10101110 5
b10011000 7
b10100000 <
1@
b1101 C
b10101110 D
#600000
0!
01
0@
#605000
1!
1$
b10101 %
b1010011 (
b1110 -
11
14
b10100001 5
b10101 7
b10011001 <
1@
b1010011 C
b10100001 D
